[
  {
    "player_id": 25711,
    "name": "Andrew Luck",
    "status": "",
    "position_type": "O",
    "eligible_positions": [
      "QB"
    ],
    "selected_position": "QB"
  },
  {
    "player_id": 25755,
    "name": "Alshon Jeffery",
    "status": "",
    "position_type": "O",
    "eligible_positions": [
      "WR"
    ],
    "selected_position": "WR"
  },
  {
    "player_id": 26699,
    "name": "Keenan Allen",
    "status": "",
    "position_type": "O",
    "eligible_positions": [
      "WR"
    ],
    "selected_position": "WR"
  },
  {
    "player_id": 26660,
    "name": "Giovani Bernard",
    "status": "",
    "position_type": "O",
    "eligible_positions": [
      "RB"
    ],
    "selected_position": "RB"
  },
  {
    "player_id": 27603,
    "name": "Tre Mason",
    "status": "",
    "position_type": "O",
    "eligible_positions": [
      "RB"
    ],
    "selected_position": "RB"
  },
  {
    "player_id": 24070,
    "name": "Jimmy Graham",
    "status": "",
    "position_type": "O",
    "eligible_positions": [
      "TE"
    ],
    "selected_position": "TE"
  },
  {
    "player_id": 27570,
    "name": "Jordan Matthews",
    "status": "",
    "position_type": "O",
    "eligible_positions": [
      "WR"
    ],
    "selected_position": "BN"
  },
  {
    "player_id": 27622,
    "name": "Terrance West",
    "status": "",
    "position_type": "O",
    "eligible_positions": [
      "RB"
    ],
    "selected_position": "BN"
  },
  {
    "player_id": 6783,
    "name": "Steven Jackson",
    "status": "",
    "position_type": "O",
    "eligible_positions": [
      "RB"
    ],
    "selected_position": "BN"
  },
  {
    "player_id": 24400,
    "name": "Chris Ivory",
    "status": "",
    "position_type": "O",
    "eligible_positions": [
      "RB"
    ],
    "selected_position": "BN"
  },
  {
    "player_id": 26273,
    "name": "Jonas Gray",
    "status": "",
    "position_type": "O",
    "eligible_positions": [
      "RB"
    ],
    "selected_position": "BN"
  },
  {
    "player_id": 24318,
    "name": "LeGarrette Blount",
    "status": "",
    "position_type": "O",
    "eligible_positions": [
      "RB"
    ],
    "selected_position": "BN"
  },
  {
    "player_id": 8832,
    "name": "Ray Rice",
    "status": "",
    "position_type": "O",
    "eligible_positions": [
      "RB"
    ],
    "selected_position": "BN"
  },
  {
    "player_id": 26534,
    "name": "Justin Tucker",
    "status": "",
    "position_type": "K",
    "eligible_positions": [
      "K"
    ],
    "selected_position": "K"
  },
  {
    "player_id": 100025,
    "name": "San Francisco",
    "status": "",
    "position_type": "DT",
    "eligible_positions": [
      "DEF"
    ],
    "selected_position": "DEF"
  },
  {
    "player_id": 100003,
    "name": "Chicago",
    "status": "",
    "position_type": "DT",
    "eligible_positions": [
      "DEF"
    ],
    "selected_position": "BN"
  }
]