[
  {
    "player_id": 24788,
    "name": "Cam Newton",
    "status": "NA",
    "position_type": "O",
    "eligible_positions": [
      "QB"
    ],
    "selected_position": "QB"
  },
  {
    "player_id": 24171,
    "name": "Antonio Brown",
    "status": "NA",
    "position_type": "O",
    "eligible_positions": [
      "WR",
      "W/R/T"
    ],
    "selected_position": "WR"
  },
  {
    "player_id": 27556,
    "name": "Kelvin Benjamin",
    "status": "NA",
    "position_type": "O",
    "eligible_positions": [
      "WR",
      "W/R/T"
    ],
    "selected_position": "WR"
  },
  {
    "player_id": 29694,
    "name": "Rob Kelley",
    "status": "NA",
    "position_type": "O",
    "eligible_positions": [
      "RB",
      "W/R/T"
    ],
    "selected_position": "RB"
  },
  {
    "player_id": 24913,
    "name": "Bilal Powell",
    "status": "NA",
    "position_type": "O",
    "eligible_positions": [
      "RB",
      "W/R/T"
    ],
    "selected_position": "RB"
  },
  {
    "player_id": 8285,
    "name": "Greg Olsen",
    "status": "NA",
    "position_type": "O",
    "eligible_positions": [
      "TE",
      "W/R/T"
    ],
    "selected_position": "TE"
  },
  {
    "player_id": 27548,
    "name": "Brandin Cooks",
    "status": "NA",
    "position_type": "O",
    "eligible_positions": [
      "WR",
      "W/R/T"
    ],
    "selected_position": "W/R/T"
  },
  {
    "player_id": 28403,
    "name": "Melvin Gordon III",
    "status": "NA",
    "position_type": "O",
    "eligible_positions": [
      "RB",
      "W/R/T"
    ],
    "selected_position": "BN"
  },
  {
    "player_id": 25876,
    "name": "Marvin Jones Jr.",
    "status": "NA",
    "position_type": "O",
    "eligible_positions": [
      "WR",
      "W/R/T"
    ],
    "selected_position": "BN"
  },
  {
    "player_id": 9265,
    "name": "Matthew Stafford",
    "status": "",
    "position_type": "O",
    "eligible_positions": [
      "QB"
    ],
    "selected_position": "BN"
  },
  {
    "player_id": 24169,
    "name": "James Starks",
    "status": "NA",
    "position_type": "O",
    "eligible_positions": [
      "RB",
      "W/R/T"
    ],
    "selected_position": "BN"
  },
  {
    "player_id": 24936,
    "name": "Dion Lewis",
    "status": "NA",
    "position_type": "O",
    "eligible_positions": [
      "RB",
      "W/R/T"
    ],
    "selected_position": "BN"
  },
  {
    "player_id": 26534,
    "name": "Justin Tucker",
    "status": "NA",
    "position_type": "K",
    "eligible_positions": [
      "K"
    ],
    "selected_position": "K"
  },
  {
    "player_id": 8432,
    "name": "Nick Folk",
    "status": "",
    "position_type": "K",
    "eligible_positions": [
      "K"
    ],
    "selected_position": "BN"
  },
  {
    "player_id": 100002,
    "name": "Buffalo",
    "status": "",
    "position_type": "DT",
    "eligible_positions": [
      "DEF"
    ],
    "selected_position": "DEF"
  },
  {
    "player_id": 100008,
    "name": "Detroit",
    "status": "",
    "position_type": "DT",
    "eligible_positions": [
      "DEF"
    ],
    "selected_position": "BN"
  },
  {
    "player_id": 100014,
    "name": "Los Angeles",
    "status": "",
    "position_type": "DT",
    "eligible_positions": [
      "DEF"
    ],
    "selected_position": "BN"
  }
]