[
  {
    "player_id": 7760,
    "name": "Jay Cutler",
    "status": "",
    "position_type": "O",
    "eligible_positions": [
      "QB"
    ],
    "selected_position": "QB"
  },
  {
    "player_id": 9496,
    "name": "Julian Edelman",
    "status": "",
    "position_type": "O",
    "eligible_positions": [
      "WR"
    ],
    "selected_position": "WR"
  },
  {
    "player_id": 7027,
    "name": "Wes Welker",
    "status": "",
    "position_type": "O",
    "eligible_positions": [
      "WR"
    ],
    "selected_position": "WR"
  },
  {
    "player_id": 9317,
    "name": "LeSean McCoy",
    "status": "",
    "position_type": "O",
    "eligible_positions": [
      "RB"
    ],
    "selected_position": "RB"
  },
  {
    "player_id": 23984,
    "name": "C.J. Spiller",
    "status": "",
    "position_type": "O",
    "eligible_positions": [
      "RB"
    ],
    "selected_position": "RB"
  },
  {
    "player_id": 24916,
    "name": "Julius Thomas",
    "status": "",
    "position_type": "O",
    "eligible_positions": [
      "TE"
    ],
    "selected_position": "TE"
  },
  {
    "player_id": 5477,
    "name": "Reggie Wayne",
    "status": "",
    "position_type": "O",
    "eligible_positions": [
      "WR"
    ],
    "selected_position": "BN"
  },
  {
    "player_id": 24822,
    "name": "Andy Dalton",
    "status": "",
    "position_type": "O",
    "eligible_positions": [
      "QB"
    ],
    "selected_position": "BN"
  },
  {
    "player_id": 8561,
    "name": "Pierre Thomas",
    "status": "",
    "position_type": "O",
    "eligible_positions": [
      "RB"
    ],
    "selected_position": "BN"
  },
  {
    "player_id": 27378,
    "name": "Khiry Robinson",
    "status": "",
    "position_type": "O",
    "eligible_positions": [
      "RB"
    ],
    "selected_position": "BN"
  },
  {
    "player_id": 24932,
    "name": "Jacquizz Rodgers",
    "status": "",
    "position_type": "O",
    "eligible_positions": [
      "RB"
    ],
    "selected_position": "BN"
  },
  {
    "player_id": 27167,
    "name": "Benny Cunningham Jr.",
    "status": "",
    "position_type": "O",
    "eligible_positions": [
      "RB"
    ],
    "selected_position": "BN"
  },
  {
    "player_id": 27709,
    "name": "Alfred Blue",
    "status": "",
    "position_type": "O",
    "eligible_positions": [
      "RB"
    ],
    "selected_position": "BN"
  },
  {
    "player_id": 26658,
    "name": "Zach Ertz",
    "status": "",
    "position_type": "O",
    "eligible_positions": [
      "TE"
    ],
    "selected_position": "BN"
  },
  {
    "player_id": 7867,
    "name": "Stephen Gostkowski",
    "status": "",
    "position_type": "K",
    "eligible_positions": [
      "K"
    ],
    "selected_position": "K"
  },
  {
    "player_id": 100033,
    "name": "Baltimore",
    "status": "",
    "position_type": "DT",
    "eligible_positions": [
      "DEF"
    ],
    "selected_position": "DEF"
  }
]