[
  {
    "player_id": 24823,
    "name": "Colin Kaepernick",
    "status": "",
    "position_type": "O",
    "eligible_positions": [
      "QB"
    ],
    "selected_position": "QB"
  },
  {
    "player_id": 27540,
    "name": "Odell Beckham Jr.",
    "status": "",
    "position_type": "O",
    "eligible_positions": [
      "WR"
    ],
    "selected_position": "WR"
  },
  {
    "player_id": 6339,
    "name": "Andre Johnson",
    "status": "",
    "position_type": "O",
    "eligible_positions": [
      "WR"
    ],
    "selected_position": "WR"
  },
  {
    "player_id": 9527,
    "name": "Arian Foster",
    "status": "",
    "position_type": "O",
    "eligible_positions": [
      "RB"
    ],
    "selected_position": "RB"
  },
  {
    "player_id": 8801,
    "name": "Chris Johnson",
    "status": "",
    "position_type": "O",
    "eligible_positions": [
      "RB"
    ],
    "selected_position": "RB"
  },
  {
    "player_id": 25703,
    "name": "Larry Donnell",
    "status": "",
    "position_type": "O",
    "eligible_positions": [
      "TE"
    ],
    "selected_position": "TE"
  },
  {
    "player_id": 27709,
    "name": "Alfred Blue",
    "status": "",
    "position_type": "O",
    "eligible_positions": [
      "RB"
    ],
    "selected_position": "BN"
  },
  {
    "player_id": 26810,
    "name": "Andre Ellington",
    "status": "",
    "position_type": "O",
    "eligible_positions": [
      "RB"
    ],
    "selected_position": "BN"
  },
  {
    "player_id": 27532,
    "name": "Sammy Watkins",
    "status": "",
    "position_type": "O",
    "eligible_positions": [
      "WR"
    ],
    "selected_position": "BN"
  },
  {
    "player_id": 24788,
    "name": "Cam Newton",
    "status": "",
    "position_type": "O",
    "eligible_positions": [
      "QB"
    ],
    "selected_position": "BN"
  },
  {
    "player_id": 27577,
    "name": "Jace Amaro",
    "status": "",
    "position_type": "O",
    "eligible_positions": [
      "TE"
    ],
    "selected_position": "BN"
  },
  {
    "player_id": 24901,
    "name": "Cecil Shorts",
    "status": "",
    "position_type": "O",
    "eligible_positions": [
      "WR"
    ],
    "selected_position": "BN"
  },
  {
    "player_id": 8982,
    "name": "Pierre Garcon",
    "status": "",
    "position_type": "O",
    "eligible_positions": [
      "WR"
    ],
    "selected_position": "BN"
  },
  {
    "player_id": 4269,
    "name": "Phil Dawson",
    "status": "",
    "position_type": "K",
    "eligible_positions": [
      "K"
    ],
    "selected_position": "K"
  },
  {
    "player_id": 100009,
    "name": "Green Bay",
    "status": "",
    "position_type": "DT",
    "eligible_positions": [
      "DEF"
    ],
    "selected_position": "DEF"
  },
  {
    "player_id": 100012,
    "name": "Kansas City",
    "status": "",
    "position_type": "DT",
    "eligible_positions": [
      "DEF"
    ],
    "selected_position": "BN"
  }
]