{
  "fantasy_content": {
    "xml:lang": "en-US",
    "yahoo:uri": "/fantasy/v2/league/331.l.145833/scoreboard;week=14",
    "league": [
      {
        "league_key": "331.l.145833",
        "league_id": "145833",
        "name": "GOODell FOR NOTHIN'",
        "url": "https://football.fantasysports.yahoo.com/2014/f1/145833",
        "logo_url": false,
        "draft_status": "postdraft",
        "num_teams": 12,
        "edit_key": "16",
        "weekly_deadline": "",
        "roster_type": "week",
        "league_update_timestamp": "1420098611",
        "scoring_type": "head",
        "league_type": "private",
        "renew": "314_214310",
        "renewed": "348_225929",
        "felo_tier": "silver",
        "is_highscore": false,
        "matchup_week": 16,
        "iris_group_chat_id": "",
        "allow_add_to_dl_extra_pos": 0,
        "is_pro_league": "0",
        "is_cash_league": "0",
        "current_week": "16",
        "start_week": "1",
        "start_date": "2014-09-04",
        "end_week": "16",
        "end_date": "2014-12-22",
        "is_finished": 1,
        "is_plus_league": "0",
        "game_code": "nfl",
        "season": "2014"
      },
      {
        "scoreboard": {
          "week": "14",
          "0": {
            "matchups": {
              "0": {
                "matchup": {
                  "week": "14",
                  "week_start": "2014-12-02",
                  "week_end": "2014-12-08",
                  "status": "postevent",
                  "is_playoffs": "1",
                  "is_consolation": "1",
                  "is_matchup_of_the_week": "0",
                  "is_matchup_recap_available": 1,
                  "matchup_recap_url": "https://football.fantasysports.yahoo.com/2014/f1/145833/recap?week=14&mid1=3&mid2=8",
                  "matchup_recap_title": "Consolation: Noodle Knee III Pulverizes BroSwithZsameHoe",
                  "matchup_grades": [
                    {
                      "matchup_grade": {
                        "team_key": "331.l.145833.t.3",
                        "grade": "A+"
                      }
                    },
                    {
                      "matchup_grade": {
                        "team_key": "331.l.145833.t.8",
                        "grade": "D"
                      }
                    }
                  ],
                  "is_tied": 0,
                  "winner_team_key": "331.l.145833.t.3",
                  "0": {
                    "teams": {
                      "0": {
                        "team": [
                          [
                            {
                              "team_key": "331.l.145833.t.3"
                            },
                            {
                              "team_id": "3"
                            },
                            {
                              "name": "Noodle Knee III"
                            },
                            [],
                            {
                              "url": "https://football.fantasysports.yahoo.com/2014/f1/145833/3"
                            },
                            {
                              "team_logos": [
                                {
                                  "team_logo": {
                                    "size": "large",
                                    "url": "https://s.yimg.com/cv/apiv2/default/nfl/nfl_9.png"
                                  }
                                }
                              ]
                            },
                            {
                              "previous_season_team_rank": 3
                            },
                            [],
                            {
                              "waiver_priority": 10
                            },
                            [],
                            {
                              "number_of_moves": 12
                            },
                            {
                              "number_of_trades": "3"
                            },
                            {
                              "roster_adds": {
                                "coverage_type": "week",
                                "coverage_value": 17,
                                "value": "0"
                              }
                            },
                            [],
                            {
                              "league_scoring_type": "head"
                            },
                            [],
                            [],
                            {
                              "has_draft_grade": 1,
                              "draft_grade": "C+",
                              "draft_recap_url": "https://football.fantasysports.yahoo.com/2014/f1/145833/3/draftrecap"
                            },
                            [],
                            [],
                            [],
                            [],
                            [],
                            {
                              "managers": [
                                {
                                  "manager": {
                                    "manager_id": "3",
                                    "nickname": "Chris D",
                                    "guid": "BOPP2W4BZXTGWKI2HFXSA4J7XQ",
                                    "image_url": "https://s.yimg.com/ag/images/4518/38724744846_904ae5_64sq.jpg",
                                    "felo_score": "544",
                                    "felo_tier": "bronze"
                                  }
                                }
                              ]
                            }
                          ],
                          {
                            "win_probability": 1,
                            "team_points": {
                              "coverage_type": "week",
                              "week": "14",
                              "total": "182.04"
                            },
                            "team_projected_points": {
                              "coverage_type": "week",
                              "week": "14",
                              "total": "129.81"
                            }
                          }
                        ]
                      },
                      "1": {
                        "team": [
                          [
                            {
                              "team_key": "331.l.145833.t.8"
                            },
                            {
                              "team_id": "8"
                            },
                            {
                              "name": "BroSwithZsameHoe"
                            },
                            [],
                            {
                              "url": "https://football.fantasysports.yahoo.com/2014/f1/145833/8"
                            },
                            {
                              "team_logos": [
                                {
                                  "team_logo": {
                                    "size": "large",
                                    "url": "https://s.yimg.com/cv/apiv2/default/nfl/nfl_11.png"
                                  }
                                }
                              ]
                            },
                            {
                              "previous_season_team_rank": 9
                            },
                            [],
                            {
                              "waiver_priority": 2
                            },
                            [],
                            {
                              "number_of_moves": 8
                            },
                            {
                              "number_of_trades": 0
                            },
                            {
                              "roster_adds": {
                                "coverage_type": "week",
                                "coverage_value": 17,
                                "value": "0"
                              }
                            },
                            [],
                            {
                              "league_scoring_type": "head"
                            },
                            [],
                            [],
                            {
                              "has_draft_grade": 1,
                              "draft_grade": "B",
                              "draft_recap_url": "https://football.fantasysports.yahoo.com/2014/f1/145833/8/draftrecap"
                            },
                            [],
                            [],
                            [],
                            [],
                            [],
                            {
                              "managers": [
                                {
                                  "manager": {
                                    "manager_id": "8",
                                    "nickname": "Scott",
                                    "guid": "M6GO4RD7WXBMO227RA6QPG7SXI",
                                    "image_url": "https://s.yimg.com/ag/images/default_user_profile_pic_64sq.jpg",
                                    "felo_score": "581",
                                    "felo_tier": "bronze"
                                  }
                                }
                              ]
                            }
                          ],
                          {
                            "win_probability": 0,
                            "team_points": {
                              "coverage_type": "week",
                              "week": "14",
                              "total": "92.37"
                            },
                            "team_projected_points": {
                              "coverage_type": "week",
                              "week": "14",
                              "total": "132.56"
                            }
                          }
                        ]
                      },
                      "count": 2
                    }
                  }
                }
              },
              "1": {
                "matchup": {
                  "week": "14",
                  "week_start": "2014-12-02",
                  "week_end": "2014-12-08",
                  "status": "postevent",
                  "is_playoffs": "1",
                  "is_consolation": "1",
                  "is_matchup_of_the_week": "0",
                  "is_matchup_recap_available": 1,
                  "matchup_recap_url": "https://football.fantasysports.yahoo.com/2014/f1/145833/recap?week=14&mid1=5&mid2=7",
                  "matchup_recap_title": "Consolation: Titsburgh Feelers Gets Comeback over Ya-Ya Smalls",
                  "matchup_grades": [
                    {
                      "matchup_grade": {
                        "team_key": "331.l.145833.t.5",
                        "grade": "C+"
                      }
                    },
                    {
                      "matchup_grade": {
                        "team_key": "331.l.145833.t.7",
                        "grade": "B"
                      }
                    }
                  ],
                  "is_tied": 0,
                  "winner_team_key": "331.l.145833.t.7",
                  "0": {
                    "teams": {
                      "0": {
                        "team": [
                          [
                            {
                              "team_key": "331.l.145833.t.5"
                            },
                            {
                              "team_id": "5"
                            },
                            {
                              "name": "Ya-Ya Smalls"
                            },
                            [],
                            {
                              "url": "https://football.fantasysports.yahoo.com/2014/f1/145833/5"
                            },
                            {
                              "team_logos": [
                                {
                                  "team_logo": {
                                    "size": "large",
                                    "url": "https://s.yimg.com/dh/ap/fantasy/img/profile_96.png"
                                  }
                                }
                              ]
                            },
                            {
                              "previous_season_team_rank": 4
                            },
                            [],
                            {
                              "waiver_priority": 8
                            },
                            [],
                            {
                              "number_of_moves": 12
                            },
                            {
                              "number_of_trades": "3"
                            },
                            {
                              "roster_adds": {
                                "coverage_type": "week",
                                "coverage_value": 17,
                                "value": "0"
                              }
                            },
                            [],
                            {
                              "league_scoring_type": "head"
                            },
                            [],
                            [],
                            {
                              "has_draft_grade": 1,
                              "draft_grade": "C",
                              "draft_recap_url": "https://football.fantasysports.yahoo.com/2014/f1/145833/5/draftrecap"
                            },
                            [],
                            [],
                            [],
                            [],
                            [],
                            {
                              "managers": [
                                {
                                  "manager": {
                                    "manager_id": "5",
                                    "nickname": "Edward Shively",
                                    "guid": "DDLJVOXLB3TBCFW2FBQI4KSYSQ",
                                    "image_url": "https://s.yimg.com/ag/images/default_user_profile_pic_64sq.jpg",
                                    "felo_score": "588",
                                    "felo_tier": "bronze"
                                  }
                                }
                              ]
                            }
                          ],
                          {
                            "win_probability": 0,
                            "team_points": {
                              "coverage_type": "week",
                              "week": "14",
                              "total": "109.73"
                            },
                            "team_projected_points": {
                              "coverage_type": "week",
                              "week": "14",
                              "total": "101.87"
                            }
                          }
                        ]
                      },
                      "1": {
                        "team": [
                          [
                            {
                              "team_key": "331.l.145833.t.7"
                            },
                            {
                              "team_id": "7"
                            },
                            {
                              "name": "Titsburgh Feelers"
                            },
                            [],
                            {
                              "url": "https://football.fantasysports.yahoo.com/2014/f1/145833/7"
                            },
                            {
                              "team_logos": [
                                {
                                  "team_logo": {
                                    "size": "large",
                                    "url": "https://s.yimg.com/cv/apiv2/default/nfl/nfl_1.png"
                                  }
                                }
                              ]
                            },
                            {
                              "previous_season_team_rank": 2
                            },
                            [],
                            {
                              "waiver_priority": 1
                            },
                            [],
                            {
                              "number_of_moves": 11
                            },
                            {
                              "number_of_trades": "4"
                            },
                            {
                              "roster_adds": {
                                "coverage_type": "week",
                                "coverage_value": 17,
                                "value": "0"
                              }
                            },
                            [],
                            {
                              "league_scoring_type": "head"
                            },
                            [],
                            [],
                            {
                              "has_draft_grade": 1,
                              "draft_grade": "B",
                              "draft_recap_url": "https://football.fantasysports.yahoo.com/2014/f1/145833/7/draftrecap"
                            },
                            [],
                            [],
                            [],
                            [],
                            [],
                            {
                              "managers": [
                                {
                                  "manager": {
                                    "manager_id": "7",
                                    "nickname": "Steph",
                                    "guid": "YN7YQQNWNDV25OIZS5FVWPNELE",
                                    "image_url": "https://s.yimg.com/ag/images/default_user_profile_pic_64sq.jpg",
                                    "felo_score": "596",
                                    "felo_tier": "bronze"
                                  }
                                }
                              ]
                            }
                          ],
                          {
                            "win_probability": 1,
                            "team_points": {
                              "coverage_type": "week",
                              "week": "14",
                              "total": "125.45"
                            },
                            "team_projected_points": {
                              "coverage_type": "week",
                              "week": "14",
                              "total": "109.04"
                            }
                          }
                        ]
                      },
                      "count": 2
                    }
                  }
                }
              },
              "2": {
                "matchup": {
                  "week": "14",
                  "week_start": "2014-12-02",
                  "week_end": "2014-12-08",
                  "status": "postevent",
                  "is_playoffs": "1",
                  "is_consolation": "0",
                  "is_matchup_of_the_week": "0",
                  "is_matchup_recap_available": 1,
                  "matchup_recap_url": "https://football.fantasysports.yahoo.com/2014/f1/145833/recap?week=14&mid1=9&mid2=12",
                  "matchup_recap_title": "Playoffs: THE TAMPA 2 Lays Waste to ManningHam N' Cheese",
                  "matchup_grades": [
                    {
                      "matchup_grade": {
                        "team_key": "331.l.145833.t.9",
                        "grade": "D"
                      }
                    },
                    {
                      "matchup_grade": {
                        "team_key": "331.l.145833.t.12",
                        "grade": "B+"
                      }
                    }
                  ],
                  "is_tied": 0,
                  "winner_team_key": "331.l.145833.t.12",
                  "0": {
                    "teams": {
                      "0": {
                        "team": [
                          [
                            {
                              "team_key": "331.l.145833.t.9"
                            },
                            {
                              "team_id": "9"
                            },
                            {
                              "name": "ManningHam N' Cheese"
                            },
                            {
                              "is_owned_by_current_login": 1
                            },
                            {
                              "url": "https://football.fantasysports.yahoo.com/2014/f1/145833/9"
                            },
                            {
                              "team_logos": [
                                {
                                  "team_logo": {
                                    "size": "large",
                                    "url": "https://s.yimg.com/cv/apiv2/default/nfl/nfl_1.png"
                                  }
                                }
                              ]
                            },
                            {
                              "previous_season_team_rank": 11
                            },
                            [],
                            {
                              "waiver_priority": 12
                            },
                            [],
                            {
                              "number_of_moves": 10
                            },
                            {
                              "number_of_trades": "2"
                            },
                            {
                              "roster_adds": {
                                "coverage_type": "week",
                                "coverage_value": 17,
                                "value": "0"
                              }
                            },
                            {
                              "clinched_playoffs": 1
                            },
                            {
                              "league_scoring_type": "head"
                            },
                            [],
                            [],
                            {
                              "has_draft_grade": 1,
                              "draft_grade": "B",
                              "draft_recap_url": "https://football.fantasysports.yahoo.com/2014/f1/145833/9/draftrecap"
                            },
                            [],
                            [],
                            [],
                            [],
                            [],
                            {
                              "managers": [
                                {
                                  "manager": {
                                    "manager_id": "9",
                                    "nickname": "Kevinchie",
                                    "guid": "GA2A2CNRUWQHL4CROE6XYLBW5A",
                                    "is_current_login": "1",
                                    "image_url": "https://s.yimg.com/ag/images/default_user_profile_pic_64sq.jpg",
                                    "felo_score": "581",
                                    "felo_tier": "bronze"
                                  }
                                }
                              ]
                            }
                          ],
                          {
                            "win_probability": 0,
                            "team_points": {
                              "coverage_type": "week",
                              "week": "14",
                              "total": "87.06"
                            },
                            "team_projected_points": {
                              "coverage_type": "week",
                              "week": "14",
                              "total": "134.67"
                            }
                          }
                        ]
                      },
                      "1": {
                        "team": [
                          [
                            {
                              "team_key": "331.l.145833.t.12"
                            },
                            {
                              "team_id": "12"
                            },
                            {
                              "name": "THE TAMPA 2"
                            },
                            [],
                            {
                              "url": "https://football.fantasysports.yahoo.com/2014/f1/145833/12"
                            },
                            {
                              "team_logos": [
                                {
                                  "team_logo": {
                                    "size": "large",
                                    "url": "https://s.yimg.com/cv/apiv2/default/nfl/nfl_2.png"
                                  }
                                }
                              ]
                            },
                            {
                              "previous_season_team_rank": 6
                            },
                            [],
                            {
                              "waiver_priority": 6
                            },
                            [],
                            {
                              "number_of_moves": 8
                            },
                            {
                              "number_of_trades": "2"
                            },
                            {
                              "roster_adds": {
                                "coverage_type": "week",
                                "coverage_value": 17,
                                "value": "0"
                              }
                            },
                            {
                              "clinched_playoffs": 1
                            },
                            {
                              "league_scoring_type": "head"
                            },
                            [],
                            [],
                            {
                              "has_draft_grade": 1,
                              "draft_grade": "B-",
                              "draft_recap_url": "https://football.fantasysports.yahoo.com/2014/f1/145833/12/draftrecap"
                            },
                            [],
                            [],
                            [],
                            [],
                            [],
                            {
                              "managers": [
                                {
                                  "manager": {
                                    "manager_id": "12",
                                    "nickname": "Kevin",
                                    "guid": "6UGHYQ44WGFQM7IMMFU3BPP3ZU",
                                    "image_url": "https://s.yimg.com/ag/images/4566/38726656651_bae4ac_64sq.jpg",
                                    "felo_score": "733",
                                    "felo_tier": "gold"
                                  }
                                },
                                {
                                  "manager": {
                                    "manager_id": "13",
                                    "nickname": "Chad",
                                    "guid": "3B7LCASSQJCVRTTSMJMRIHFORI",
                                    "is_comanager": "1",
                                    "image_url": "https://s.yimg.com/ag/images/default_user_profile_pic_64sq.jpg",
                                    "felo_score": "575",
                                    "felo_tier": "bronze"
                                  }
                                }
                              ]
                            }
                          ],
                          {
                            "win_probability": 1,
                            "team_points": {
                              "coverage_type": "week",
                              "week": "14",
                              "total": "149.88"
                            },
                            "team_projected_points": {
                              "coverage_type": "week",
                              "week": "14",
                              "total": "137.36"
                            }
                          }
                        ]
                      },
                      "count": 2
                    }
                  }
                }
              },
              "3": {
                "matchup": {
                  "week": "14",
                  "week_start": "2014-12-02",
                  "week_end": "2014-12-08",
                  "status": "postevent",
                  "is_playoffs": "1",
                  "is_consolation": "0",
                  "is_matchup_of_the_week": "0",
                  "is_matchup_recap_available": 1,
                  "matchup_recap_url": "https://football.fantasysports.yahoo.com/2014/f1/145833/recap?week=14&mid1=10&mid2=11",
                  "matchup_recap_title": "Playoffs: Jacob's Team Gets Win over Tears of Boston",
                  "matchup_grades": [
                    {
                      "matchup_grade": {
                        "team_key": "331.l.145833.t.10",
                        "grade": "B"
                      }
                    },
                    {
                      "matchup_grade": {
                        "team_key": "331.l.145833.t.11",
                        "grade": "D+"
                      }
                    }
                  ],
                  "is_tied": 0,
                  "winner_team_key": "331.l.145833.t.10",
                  "0": {
                    "teams": {
                      "0": {
                        "team": [
                          [
                            {
                              "team_key": "331.l.145833.t.10"
                            },
                            {
                              "team_id": "10"
                            },
                            {
                              "name": "Jacob's Team"
                            },
                            [],
                            {
                              "url": "https://football.fantasysports.yahoo.com/2014/f1/145833/10"
                            },
                            {
                              "team_logos": [
                                {
                                  "team_logo": {
                                    "size": "large",
                                    "url": "https://s.yimg.com/cv/apiv2/default/nfl/nfl_1.png"
                                  }
                                }
                              ]
                            },
                            {
                              "previous_season_team_rank": 5
                            },
                            [],
                            {
                              "waiver_priority": 3
                            },
                            [],
                            {
                              "number_of_moves": 11
                            },
                            {
                              "number_of_trades": "4"
                            },
                            {
                              "roster_adds": {
                                "coverage_type": "week",
                                "coverage_value": 17,
                                "value": "0"
                              }
                            },
                            {
                              "clinched_playoffs": 1
                            },
                            {
                              "league_scoring_type": "head"
                            },
                            [],
                            [],
                            {
                              "has_draft_grade": 1,
                              "draft_grade": "B",
                              "draft_recap_url": "https://football.fantasysports.yahoo.com/2014/f1/145833/10/draftrecap"
                            },
                            [],
                            [],
                            [],
                            [],
                            [],
                            {
                              "managers": [
                                {
                                  "manager": {
                                    "manager_id": "10",
                                    "nickname": "--hidden--",
                                    "guid": "--",
                                    "felo_score": "692",
                                    "felo_tier": "silver"
                                  }
                                }
                              ]
                            }
                          ],
                          {
                            "win_probability": 1,
                            "team_points": {
                              "coverage_type": "week",
                              "week": "14",
                              "total": "150.08"
                            },
                            "team_projected_points": {
                              "coverage_type": "week",
                              "week": "14",
                              "total": "133.25"
                            }
                          }
                        ]
                      },
                      "1": {
                        "team": [
                          [
                            {
                              "team_key": "331.l.145833.t.11"
                            },
                            {
                              "team_id": "11"
                            },
                            {
                              "name": "Tears of Boston"
                            },
                            [],
                            {
                              "url": "https://football.fantasysports.yahoo.com/2014/f1/145833/11"
                            },
                            {
                              "team_logos": [
                                {
                                  "team_logo": {
                                    "size": "large",
                                    "url": "https://s.yimg.com/cv/apiv2/default/nfl/nfl_3.png"
                                  }
                                }
                              ]
                            },
                            {
                              "previous_season_team_rank": 12
                            },
                            [],
                            {
                              "waiver_priority": 4
                            },
                            [],
                            {
                              "number_of_moves": 12
                            },
                            {
                              "number_of_trades": "2"
                            },
                            {
                              "roster_adds": {
                                "coverage_type": "week",
                                "coverage_value": 17,
                                "value": "0"
                              }
                            },
                            {
                              "clinched_playoffs": 1
                            },
                            {
                              "league_scoring_type": "head"
                            },
                            [],
                            [],
                            {
                              "has_draft_grade": 1,
                              "draft_grade": "C+",
                              "draft_recap_url": "https://football.fantasysports.yahoo.com/2014/f1/145833/11/draftrecap"
                            },
                            [],
                            [],
                            [],
                            [],
                            [],
                            {
                              "managers": [
                                {
                                  "manager": {
                                    "manager_id": "11",
                                    "nickname": "Kenneth Smith",
                                    "guid": "RXICUQGFSZDLSOLDXZPBGWMO5U",
                                    "image_url": "https://s.yimg.com/ag/images/default_user_profile_pic_64sq.jpg",
                                    "felo_score": "571",
                                    "felo_tier": "bronze"
                                  }
                                }
                              ]
                            }
                          ],
                          {
                            "win_probability": 0,
                            "team_points": {
                              "coverage_type": "week",
                              "week": "14",
                              "total": "107.71"
                            },
                            "team_projected_points": {
                              "coverage_type": "week",
                              "week": "14",
                              "total": "123.47"
                            }
                          }
                        ]
                      },
                      "count": 2
                    }
                  }
                }
              },
              "count": 4
            }
          }
        }
      }
    ],
    "time": "459.33699607849ms",
    "copyright": "Certain Data by Sportradar, Stats Perform and Rotowire",
    "refresh_rate": "60"
  }
}